{
  "collapseBooleanAttributes": true,
  "collapseWhitespace": true,
  "html5": true,
  "removeAttributeQuotes": true,
  "removeComments": true,
  "removeEmptyAttributes": true,
  "removeEmptyElements": true,
  "removeOptionalTags": true,
  "removeRedundantAttributes": true,
  "removeScriptTypeAttributes": true,
  "removeStyleLinkTypeAttributes": true,
  "removeTagWhitespace": true,
  "sortAttributes": true,
  "sortClassName": true,
  "trimCustomFragments": true,
  "useShortDoctype": true,
  "minifyJS": {
    "mangle": { "toplevel": true, "eval": true, "reserved" :
    ["showImage", "initializeDocumentObjects", "loadFromQueryString",
    "hideCustomAlert", "mapmousedown", "mapmousemove", "mapmouseup",
    "menuImageOver", "menuImageIn", "zoom"]}
  },
  "includeAutoGeneratedTags": false
}
