{
  "collapseBooleanAttributes": true,
  "collapseWhitespace": true,
  "html5": true,
  "includeAutoGeneratedTags": false,
  "minifyJS": {
    "compress": {
      "inline": true,
      "unsafe": true,
      "passes": 2
    },
    "ie": true,
    "mangle": {
      "eval": true,
      "reserved": ["x", "y", "w", "f", "R", "F", "E"],
      "toplevel": true
    },
    "nameCache": {}
  },
  "removeAttributeQuotes": true,
  "removeComments": true,
  "removeEmptyAttributes": true,
  "removeEmptyElements": false,
  "removeOptionalTags": true,
  "removeRedundantAttributes": true,
  "removeScriptTypeAttributes": true,
  "removeStyleLinkTypeAttributes": true,
  "removeTagWhitespace": true,
  "sortAttributes": true,
  "sortClassName": true,
  "trimCustomFragments": true,
  "useShortDoctype": true
}
